hierophant/__init__.py
hierophant/explainer.py
hierophant/explorer.py
hierophant/statistics.py
hierophant/templates.py
hierophant-0.1.11.dist-info/LICENSE
hierophant-0.1.11.dist-info/METADATA
hierophant-0.1.11.dist-info/WHEEL
hierophant-0.1.11.dist-info/RECORD
