Metadata-Version: 2.1
Name: hierophant
Version: 0.1.11
Summary: Explainable AI with Large Language Models
License: MIT
Author: chrisaddy
Author-email: chris.william.addy@gmail.com
Requires-Python: >=3.8,<3.12
Classifier: License :: OSI Approved :: MIT License
Classifier: Programming Language :: Python :: 3
Classifier: Programming Language :: Python :: 3.8
Classifier: Programming Language :: Python :: 3.9
Classifier: Programming Language :: Python :: 3.10
Classifier: Programming Language :: Python :: 3.11
Requires-Dist: openai (>=0.27.8,<0.28.0)
Requires-Dist: torch (>=2.0.1,<3.0.0)
Requires-Dist: ydata-profiling (>=4.5.1,<5.0.0)
